{
  "db_name": "PostgreSQL",
  "query": "UPDATE scheduled_batches\n             SET status       = 'pending',\n                 retry_count  = retry_count + 1,\n                 scheduled_at = $1,\n                 last_error   = $2\n             WHERE id = $3",
  "describe": {
    "columns": [],
    "parameters": {
      "Left": [
        "Timestamptz",
        "Text",
        "Uuid"
      ]
    },
    "nullable": []
  },
  "hash": "308b416ed06beed05df1619e415b9402bb024c9fa6e859814229848af474761d"
}
